{
    "type": "FeatureCollection",
    "features": [
        {
            "type": "Feature",
            "geometry": {
                "type": "LineString",
                "coordinates": [
                    [
                        100.51926,
                        13.72322,
                        0
                    ],
                    [
                        100.51951,
                        13.7233,
                        0
                    ],
                    [
                        100.51976,
                        13.72337,
                        0
                    ],
                    [
                        100.51987,
                        13.7234,
                        0
                    ],
                    [
                        100.51997,
                        13.72343,
                        0
                    ],
                    [
                        100.52005,
                        13.723460000000001,
                        0
                    ],
                    [
                        100.52014,
                        13.72348,
                        0
                    ],
                    [
                        100.52019000000001,
                        13.7235,
                        0
                    ],
                    [
                        100.52056,
                        13.72365,
                        0
                    ],
                    [
                        100.52066,
                        13.72369,
                        0
                    ],
                    [
                        100.52089000000001,
                        13.72379,
                        0
                    ],
                    [
                        100.52097000000002,
                        13.72382,
                        0
                    ],
                    [
                        100.52131,
                        13.72396,
                        0
                    ],
                    [
                        100.52148,
                        13.72402,
                        0
                    ],
                    [
                        100.52166,
                        13.72408,
                        0
                    ],
                    [
                        100.52171,
                        13.7241,
                        0
                    ],
                    [
                        100.52176,
                        13.72412,
                        0
                    ],
                    [
                        100.52189,
                        13.72417,
                        0
                    ],
                    [
                        100.52203,
                        13.72423,
                        0
                    ],
                    [
                        100.52207,
                        13.72424,
                        0
                    ],
                    [
                        100.52211,
                        13.72426,
                        0
                    ],
                    [
                        100.5223,
                        13.72434,
                        0
                    ],
                    [
                        100.5225,
                        13.72442,
                        0
                    ],
                    [
                        100.52258,
                        13.72445,
                        0
                    ],
                    [
                        100.52267,
                        13.72448,
                        0
                    ],
                    [
                        100.52274,
                        13.7245,
                        0
                    ],
                    [
                        100.52281,
                        13.72453,
                        0
                    ],
                    [
                        100.52294,
                        13.72458,
                        0
                    ],
                    [
                        100.52307,
                        13.72462,
                        0
                    ],
                    [
                        100.52345,
                        13.72476,
                        0
                    ],
                    [
                        100.5239,
                        13.72492,
                        0
                    ],
                    [
                        100.52403,
                        13.72497,
                        0
                    ],
                    [
                        100.52407,
                        13.72498,
                        0
                    ],
                    [
                        100.52439,
                        13.72509,
                        0
                    ],
                    [
                        100.52470000000001,
                        13.7252,
                        0
                    ],
                    [
                        100.525,
                        13.725300000000002,
                        0
                    ],
                    [
                        100.52518,
                        13.72536,
                        0
                    ],
                    [
                        100.52554,
                        13.72547,
                        0
                    ],
                    [
                        100.52565000000001,
                        13.7255,
                        0
                    ],
                    [
                        100.52576,
                        13.72554,
                        0
                    ],
                    [
                        100.52588,
                        13.72559,
                        0
                    ],
                    [
                        100.52602,
                        13.72564,
                        0
                    ],
                    [
                        100.5262,
                        13.7257,
                        0
                    ],
                    [
                        100.52635000000001,
                        13.72576,
                        0
                    ],
                    [
                        100.52661,
                        13.72585,
                        0
                    ],
                    [
                        100.52675,
                        13.7259,
                        0
                    ],
                    [
                        100.527,
                        13.72599,
                        0
                    ],
                    [
                        100.52739,
                        13.72612,
                        0
                    ],
                    [
                        100.52752,
                        13.72617,
                        0
                    ],
                    [
                        100.52771,
                        13.72624,
                        0
                    ],
                    [
                        100.52790000000002,
                        13.72631,
                        0
                    ]
                ]
            },
            "properties": {
                "name": "Directions from 162 Sathon Nuea Rd, Khwaeng Silom, Khet Bang Rak, Krung Thep Maha Nakhon 10500, Thailand to 152/8-9 Silom Rd, Khwaeng Suriya Wong, Khet Bang Rak, Krung Thep Maha Nakhon 10500, Thailand"
            }
        }
    ]
}